fastapi_ipware/__init__.py
fastapi_ipware-0.1.2.dist-info/WHEEL
fastapi_ipware-0.1.2.dist-info/METADATA
fastapi_ipware-0.1.2.dist-info/RECORD
