Metadata-Version: 2.3
Name: fastapi-ipware
Version: 0.1.2
Summary: FastAPI/Starlette-native wrapper for python-ipware to get client IP addresses
Keywords: fastapi,starlette,ipware,ip-address,client-ip,proxy,x-forwarded-for
Author: Michael Bianco
Author-email: Michael Bianco <mike@mikebian.co>
Requires-Dist: python-ipware>=3.0.0
Requires-Dist: starlette>=0.49.1
Requires-Python: >=3.10
Project-URL: Repository, https://github.com/iloveitaly/fastapi-ipware
